#######################################################################################################################################
<poster>One242415</poster>
<fanart></fanart>
#######################################################################################################################################
<info>
<message></message> 
<thumbnail></thumbnail>
</info>
##############################################################################################################################

<item>
<title>La mia classe (2013)</title>
<link>http://played.to/0dmavqxev2ex</link>
<thumbnail>http://pad.mymovies.it/filmclub/2013/07/067/locandina.jpg</thumbnail>
</item>

<item>
<title>Anni felici (2013)</title>
<link>http://www.uploadc.com/pk913go0jpea</link>
<thumbnail>http://static.mediabang.org/posters/429/429407_those_happy_years_2013.jpg</thumbnail>
</item>























