#######################################################################################################################################
<poster>One242415</poster>
<fanart></fanart>
#######################################################################################################################################
<info>
<message></message> 
<thumbnail></thumbnail>
</info>
##############################################################################################################################

<item>
<title>Grand Canyon: National Parks Collection (2009)</title>
<link>http://www.firedrive.com/file/7492E6890F5385DE</link>
<thumbnail>http://ecx.images-amazon.com/images/I/516WZeWLRBL.jpg</thumbnail>
</item>

<item>Extreme Alaska Denali National Park (2008)</title>
<link>http://www.sockshare.com/file/07FD18C532E0F841#</link>
<thumbnail>http://media-cache-cd0.pinimg.com/736x/c0/07/13/c007135f97a0ac539c1843383dcf61d6.jpg</thumbnail>
</item>

<item>
<title>Kissinger (2011)</title>
<link>http://www.sockshare.com/file/FC52C9F77208118C#</link>
<thumbnail>http://1.bp.blogspot.com/-JZDSa-JHMnA/TnHoNHThnRI/AAAAAAAAMKE/sVQ0XE2GBZ8/s1600/Kissinger%2B%25282011%2529.jpg</thumbnail>
</item>

<item>
<title>Ipredator (2011)</title>
<link>http://www.firedrive.com/file/66D555CE8CF8AD3C</link>
<thumbnail>http://www.dvdandgifts.co.za/images/National%20Geo%20-%20Last%20feast%20of%20the%20crocodiles.jpg</thumbnail>
</item>

<item>
<title>Vampires (2010)</title>
<link>http://www.firedrive.com/file/BD942B9D9F0B1FC3</link>
<thumbnail>http://www.horrorphile.net/images/national-geographic-vampire-forensics-dvd-cover-ar1.jpg</thumbnail>
</item>

<item>
<title>Everglades (2009)</title>
<link>http://www.sockshare.com/file/D6EE66CD910C0D61#</link>
<thumbnail>http://www4.alibris-static.com/cover/u75331ssmll.jpg</thumbnail>
</item>

<item>
<title>Yellowstone (2011)</title>
<link>http://www.nowvideo.sx/video/tejplgfhsrplc</link>
<thumbnail>http://i.imgur.com/PUw58.jpg</thumbnail>
</item>

<item>
<title>DogTown (2009)</title>
<link>http://www.sockshare.com/file/66C2BF8D9C606D88#</link>
<thumbnail>http://www.dvd-bluray-reviews.com/big_images/dvd/National-Geographic-Dogtown---Friends-in-Need.jpg</thumbnail>
</item>

<item>
<title>Solitary Confinement (2010)</title>
<link>http://www.sockshare.com/file/69786608E2442365#</link>
<thumbnail>http://static1.vidics.ch/150/2/National_Geographic_Solitary_Confinement-39815.PNG</thumbnail>
</item>

<item>
<title>Brothers In War (2014)</title>
<link>http://vidbull.com/34br5utjsx2k.html</link>
<thumbnail>http://i.imgur.com/FJRS99D.jpg</thumbnail>
</item>

<item>
<title>National Geographic at 125 (2013)</title>
<link>http://www.nowvideo.sx/video/532454adb29e2</link>
<thumbnail>http://press.nationalgeographic.com/files/2013/01/usa_today_ng_125_cover-2-393x400.jpg</thumbnail>
</item>

<item>
<title>The Lion Whisper (2014)</title>
<link>http://played.to/6vgohxi068nv</link>
<thumbnail>http://media-cache-cd0.pinimg.com/236x/e8/61/f1/e861f14cbfd07009a6280f5d02e723ea.jpg</thumbnail>
</item>

<item>
<title>Wild Phantom Cat (2014)</title>
<link>http://played.to/azyyr6aev7zf</link>
<thumbnail>http://channel.nationalgeographic.com/exposure/content/photo/photo/663010_cat-nap_7hqdjmj4am3d2cszxsyeykq4xpncurxrbvj6lwuht2ya6mzmafma_610x457.jpg</thumbnail>
</item>

<item>
<title>Flying Squad The Real Sweeney (2014)</title>
<link>http://www.sockshare.com/file/52EE0134F9BC538A#</link>
<thumbnail>http://img.rlsbb.com/images/2014/02/05/7cec6356be14e42ffbbb21f7a7bc5f4e.jpg</thumbnail>
</item>

<item>
<title>Miracle Landing on the Hudson (2014)</title>
<link>http://www.nowvideo.sx/video/e1b6b17c99075</link>
<thumbnail>https://encrypted-tbn0.gstatic.com/images?q=tbn:ANd9GcRkzL6NjcxXqkMwy2rXKEbQmp7DixHi5-wFqNzFZKzM0NKZsQW_</thumbnail>
</item>

<item>
<title>Secret Service Files: Protecting the President (2013)</title>
<link>http://www.divxstage.eu/video/528a0277d733f</link>
<thumbnail>http://dokonline.com/uploads/posts/2013-02/1360088929_1.jpg</thumbnail>
</item>

<item>
<title>Nazi Underworld The Hess Enigma (2013)</title>
<link>http://www.nowvideo.sx/video/4a800e72d786f</link>
<thumbnail>http://yuq.me/tv/16/683/34067.jpg</thumbnail>
</item>

<item>
<title>American Blackout (2013) </title>
<link>http://www.divxstage.eu/video/526ed86e4918f</link>
<thumbnail>http://channel.nationalgeographic.com/exposure/content/photo/photo/2074272_american-blackout_yhhbui2h6fubfdyfdbahdhdawlncurxrbvj6lwuht2ya6mzmafma_740x416.jpg</thumbnail>
</item>

<item>
<title>Nazi Underworld Patient Hitler (2013)</title>
<link>http://www.nowvideo.sx/video/3wwpa9amr6uqf</link>
<thumbnail>http://rapidmoviez.com/data/images/movies/2013-07/nazi-underworld.jpg</thumbnail>
</item>

<item>
<title>9 11 Firehouse Ground Zero (2013)</title>
<link>http://www.nowvideo.sx/video/8tbvmv44o06ez</link>
<thumbnail>http://pixhost.me/avaxhome/78/59/00285978_medium.jpeg</thumbnail>
</item>

<item>
<title>World's Deadliest Lady Killers (2013)</title>
<link>http://www.nowvideo.sx/video/5a15b425bab61</link>
<thumbnail>http://b.vimeocdn.com/ts/454/535/454535057_640.jpg</thumbnail>
</item>

<item>
<title>Breakout The Texas Seven (2013)</title>
<link>http://www.nowvideo.sx/video/98d92c242c8e7</link>
<thumbnail>http://2.bp.blogspot.com/-FxW-ViXRkeM/Um__HfjrtkI/AAAAAAAAFMk/g3eXxtGKvlk/s1600/2741472_National_Geographic_Breakout_The_Texas_Seven.jpg</thumbnail>
</item>

<item>
<title>Machu Picchu Decoded (2009)</title>
<link>http://filenuke.com/hel4197km15b</link>
<thumbnail>http://rapidmoviez.com/data/images/movies/2014-01/national-geographic--machu-picchu-decoded.jpg</thumbnail>
</item>




















