#######################################################################################################################################
<poster>One242415</poster>
<fanart></fanart>
#######################################################################################################################################
<info>
<message></message> 
<thumbnail></thumbnail>
</info>
##############################################################################################################################






<item>
<title>The Visitant (2012) 720p</title>
<link>http://hugefiles.net/amhjiv6eic4m</link>
<thumbnail>http://ia.media-imdb.com/images/M/MV5BMjIyMjczMjU3MF5BMl5BanBnXkFtZTcwOTQwMjYzOQ@@._V1_SX500_SY999_.jpg</thumbnail>
</item>

<item>
<title>Vamps (2012)</title>
<link>http://movreel.com/2fbdhopejsle</link>
<thumbnail>http://www.aceshowbiz.com/images/still/vamps-poster02.jpg</thumbnail>
</item>

<item>
<title>Le Week-End (2013) 720p</title>
<link>http://movreel.com/fj1b6fw3n9ex</link>
<thumbnail>http://ia.media-imdb.com/images/M/MV5BMTk3NzAxNTExMF5BMl5BanBnXkFtZTgwMDM0NjYwMTE@._V1_SX500_SY999_.jpg</thumbnail>
</item>

<item>
<title>The Gabby Douglas Story (TV Movie 2014)</title>
<link>http://movreel.com/el6tct7h5p8q</link>
<thumbnail>http://ia.media-imdb.com/images/M/MV5BMjA0ODM1NTMwNV5BMl5BanBnXkFtZTgwMjU5ODUwMTE%40._V1_SY317_SX214_.jpg</thumbnail>
</item>

<item>
<title>Two Jacks (2012)</title>
<link>http://movreel.com/72vhvizajsth#</link>
<thumbnail>http://ia.media-imdb.com/images/M/MV5BMTUyNjkyNjY1Nl5BMl5BanBnXkFtZTgwMjEwMTgyMDE%40._V1_SX214_.jpg</thumbnail>
</item>

<item>
<title>Stay (2013)</title>
<link>http://movreel.com/gjaf7y0ntmyy#</link>
<thumbnail>http://ia.media-imdb.com/images/M/MV5BMTQxODgwNDM5OF5BMl5BanBnXkFtZTgwNjg4NjYxMTE@._V1_SX500_SY999_.jpg</thumbnail>
</item>

<item>
<title>Reaching For The Moon(2013)</title>
<link>http://movreel.com/4n5yl56zrnv3#</link>
<thumbnail>http://movies-singapore.com/wp-content/uploads/2013/08/reaching-for-the-moon-2013-poster.jpg</thumbnail>
</item>

<item>
<title>Anna Nicole (TV Movie 2013)</title>
<link>http://movreel.com/4ec1hfje77fk#</link>
<thumbnail>http://2.bp.blogspot.com/-c7sp_zoWx5I/Uolr8vIJUWI/AAAAAAAAE3w/fNXvcpmPrMU/s1600/o_anna-nicole-2013-original-lifetime-tv-movie-dvd-38fa.jpg</thumbnail>
</item>

<item>
<title>Knights of Badassdom (2013)</title>
<link>http://movreel.com/4x9lgk8gm4t6#</link>
<thumbnail>http://ia.media-imdb.com/images/M/MV5BMTQ3ODEwMzY3NV5BMl5BanBnXkFtZTgwNTkwMTQ5MDE%40._V1_SY1200_CR90,0,630,1200_.jpg</thumbnail>
</item>

<item>
<title>Old Boy(2013)</title>
<link>http://vidto.me/5otjinfsov6i</link>
<thumbnail>http://img2.timeinc.net/ew/i/2013/10/10/OLDBOY_800x1236.jpg</thumbnail>
</item>

<item>
<title>Nurse 3-D (2013)</title>
<link>http://hugefiles.net/8xy4l7ye8gp7</link>
<thumbnail>http://ia.media-imdb.com/images/M/MV5BMjM4MjYwMjQ2Nl5BMl5BanBnXkFtZTgwMTkxODM1MDE%40._V1_SX214_.jpg</thumbnail>
</item>

<item>
<title>The Wolf of Wall Street (2013)</title>
<link>http://movreel.com/rlqpz9a250bq#</link>
<thumbnail>http://ia.media-imdb.com/images/M/MV5BMjIxMjgxNTk0MF5BMl5BanBnXkFtZTgwNjIyOTg2MDE%40._V1_SX640_SY720_.jpg</thumbnail>
</item>

<item>
<title>The Trials of Cate McCall (2013)</title>
<link>http://www.putlocker.com/file/67A2BED4A868F9F4#</link>
<thumbnail>http://ia.media-imdb.com/images/M/MV5BMTQ0MTUwNjI4MF5BMl5BanBnXkFtZTgwOTk4MDk3MDE%40._V1_SX214_.jpg</thumbnail>
</item>

<item>
<title>The Art of the Steal (2013)</title>
<link>http://www.putlocker.com/file/7C490F820A71BEA9#</link>
<thumbnail>http://upload.wikimedia.org/wikipedia/en/b/bc/The_Art_of_the_Steal_poster.jpg</thumbnail>
</item>

<item>
<title>Philomena (2013)</title>
<link>http://www.putlocker.com/file/EC321DC3B77A9257#</link>
<thumbnail>https://encrypted-tbn1.gstatic.com/images?q=tbn:ANd9GcTyWzmx6WGXcupY75d8TmFH7TiR1zfP8DACHR0G3GMRAfP3rBYWqA</thumbnail>
</item>

<item>
<title>The Wedding Pact (2014)</title>
<link>http://www.putlocker.com/file/20D34F0530DDAE8A#</link>
<thumbnail>http://ia.media-imdb.com/images/M/MV5BMTY4MTAzOTkwNV5BMl5BanBnXkFtZTgwMDc4MDk3MDE%40._V1_SY317_CR8,0,214,317_.jpg</thumbnail>
</item>

<item>
<title>Nebraska (2013)</title>
<link>http://vidto.me/uo21u3rtbx72</link>
<thumbnail>https://encrypted-tbn2.gstatic.com/images?q=tbn:ANd9GcQBNI1wtb9dSEcCr1BEgN09JfooLEjog65Gk0xu0zMOcxP4Eiuf</thumbnail>
</item>

<item>
<title>Gingerclown (2013)</title>
<link>http://www.nowvideo.sx/video/f9817a31a34ae</link>
<thumbnail>http://www.aceshowbiz.com/images/still/gingerclown-3d-poster02.jpg</thumbnail>
</item>


<item>
<title>Critical Nexus (2013)</title>
<link>http://www.putlocker.com/file/0670EA4EDF1D2F62#</link>
<thumbnail>http://ia.media-imdb.com/images/M/MV5BOTYyNDg2MDI4MF5BMl5BanBnXkFtZTgwNDQzNTUzMDE%40._V1_SX640_SY720_.jpg</thumbnail>
</item>

<item>
<title>House of Bodies (2013)</title>
<link>http://www.nowvideo.sx/video/52ed77fd1a8fe</link>
<thumbnail>http://www.blackfilm.com/read/wp-content/uploads/2014/01/House-of-Bodies-DVD.jpg</thumbnail>
</item>


<item>
<title>Finding Mrs. Claus (TV Movie 2012)</title>
<link>http://movreel.com/kxbdg99gyilg#</link>
<thumbnail>http://i.imgur.com/pKUSgHr.jpg</thumbnail>
</item>

<item>
<title>The Hungover Games (2014)</title>
<link>http://movreel.com/z5rqo8ylqzrf#</link>
<thumbnail>http://ia.media-imdb.com/images/M/MV5BMTk0NjM3MDk3NV5BMl5BanBnXkFtZTgwNTEzNTY3MDE%40._V1_SY317_CR5,0,214,317_.jpg</thumbnail>
</item>

<item>
<title>Ride Along (2014)</title>
<link>http://vidto.me/xf15udkibsiz.html</link>
<thumbnail>http://www.aceshowbiz.com/images/still/ride-along-poster01.jpg</thumbnail>
</item>

<item>
<title>Grand Piano (2013) 720P</title>
<link>http://movreel.com/3zbilisbsc6r#</link>
<thumbnail>http://ia.media-imdb.com/images/M/MV5BMjEyNzkwMDMxM15BMl5BanBnXkFtZTgwOTM0MzE4MDE%40._V1_SX214_.jpg</thumbnail>
</item>


<item>
<title>Homefront (2013)</title>
<link>http://movreel.com/bvdd24n0td9f#</link>
<thumbnail>http://ia.media-imdb.com/images/M/MV5BMTUwOTAzNzAwMl5BMl5BanBnXkFtZTgwOTc1NDIyMDE%40._V1_SX640_SY720_.jpg</thumbnail>
</item>

<item>
<title>California Scheming (2014) 720P</title>
<link>http://movreel.com/6cf62xrazveq#</link>
<thumbnail>http://ia.media-imdb.com/images/M/MV5BMjExOTc4NTk1NF5BMl5BanBnXkFtZTgwODMyMzY0MDE%40._V1_SY317_CR0,0,214,317_.jpg</thumbnail>
</item>


<item>
<title>Welcome to the Jungle (2013)</title>
<link>http://played.to/mf33tdm16tnk</link>
<thumbnail>https://encrypted-tbn2.gstatic.com/images?q=tbn:ANd9GcRRkKQzzw8IQMapu5JB_8_VMKGk28qRw1W1ZXw8GcBCtj6-YunX</thumbnail>
</item>


<item>
<title>Thor: The Dark World (2013) 720p</title>
<link>http://movreel.com/a28uxc9zb6k4#</link>
<thumbnail>http://www.impawards.com/2013/posters/thor_the_dark_world.jpg</thumbnail>
</item>


<item>
<title>Run (2013)</title>
<link>http://movreel.com/xmklqpa1ef97#</link>
<thumbnail>http://ia.media-imdb.com/images/M/MV5BMTQzNDk1NDY1M15BMl5BanBnXkFtZTgwNzA5OTIyMDE@._V1_SX640_SY720_.jpg</thumbnail>
</item>


<item>
<title>Grace Unplugged (2013) 720p</title>
<link>http://movreel.com/dgc6nj9q14ad#</link>
<thumbnail>http://www.christiancinema.com/catalog/images/GraceUnpluggedPoster.jpg</thumbnail>
</item>


<item>
<title>The Counselor (2013) 720p</title>
<link>http://www.nowvideo.sx/video/719b190c63701</link>
<thumbnail>http://ia.media-imdb.com/images/M/MV5BMTc3ODk0MTY0N15BMl5BanBnXkFtZTgwOTU2MTEzMDE%40._V1_SX640_SY720_.jpg</thumbnail>
</item>


<item>
<title>Sunshine on Leith (2013)</title>
<link>http://movreel.com/3uxfz1retkbg#</link>
<thumbnail>http://ia.media-imdb.com/images/M/MV5BODIyNzU0NDYzM15BMl5BanBnXkFtZTgwNzM5NjUzMDE%40._V1_SX214_.jpg</thumbnail>
</item>

<item>
<title>Margarita (2012)</title>
<link>http://www.putlocker.com/file/CF9C41899AFEBA73#</link>
<thumbnail>http://ia.media-imdb.com/images/M/MV5BNzcwODg2NDI5OF5BMl5BanBnXkFtZTgwMTkxNzA2MDE%40._V1_SX214_.jpg</thumbnail>
</item>


<item>
<title>Afternoon Delight (2013)</title>
<link>http://www.nowvideo.sx/video/38ef372c9b261</link>
<thumbnail>http://d1oi7t5trwfj5d.cloudfront.net/63/f5/8cb0a39840118433d12599ed4db6/afternoon-delight-poster.jpg</thumbnail>
</item>


<item>
<title>Gloria (2013)</title>
<link>http://hugefiles.net/que74igmcu2b</link>
<thumbnail>http://ia.media-imdb.com/images/M/MV5BMzI1NjgxNDM3N15BMl5BanBnXkFtZTgwMTI4MDI1MDE%40._V1_SX640_SY720_.jpg</thumbnail>
</item>


<item>
<title>Dracula 3D (2012)</title>
<link>http://vidto.me/0599wwubylqo.html</link>
<thumbnail>http://2.bp.blogspot.com/-EnU3FA-cPCU/UbEKgZTH1VI/AAAAAAAAawM/yRZXwBY6p5s/s640/8aeddd83ae44719ca995f3793a5ff62c.jpg</thumbnail>
</item>


<item>
<title>Concrete Blondes (2012)</title>
<link>http://movreel.com/uibjmhsamf2p#</link>
<thumbnail>http://ia.media-imdb.com/images/M/MV5BMTQ1NjMwNTg2M15BMl5BanBnXkFtZTcwMzYyMTc5Nw%40%40._V1_SX640_SY720_.jpg</thumbnail>
</item>


<item>
<title>Salinger (2013)</title>
<link>http://www.nowvideo.sx/video/a1d451bbbe284</link>
<thumbnail>http://www.hollywoodreporter.com/sites/default/files/custom/Salinger_Poster_embed_article.jpg</thumbnail>
</item>


<item>
<title>Return to Nuke 'Em High Volume 1 (2013)</title>
<link>http://movreel.com/enhgfwl14vks#</link>
<thumbnail>http://moviebuzzers.com/wp-content/uploads/2013/07/Return-to-Nuke-Em-High-Volume-1-poster.jpg</thumbnail>
</item>


<item>
<title>The Black Water Vampire (2014)</title>
<link>http://180upload.com/c70u9uolrig7#</link>
<thumbnail>http://ia.media-imdb.com/images/M/MV5BMTg2ODI0Mjc1OF5BMl5BanBnXkFtZTgwNTUyNDY4MDE%40._V1_SX214_.jpg</thumbnail>
</item>


<item>
<title>Dead of the Nite (2013)</title>
<link>http://movreel.com/068ol8tdox1s#</link>
<thumbnail>http://ia.media-imdb.com/images/M/MV5BMjIzMzg4NTY5NF5BMl5BanBnXkFtZTcwMjI1NDA1Ng%40%40._V1_SX214_.jpg</thumbnail>
</item>


<item>
<title>Interior. Leather Bar. (2013)</title>
<link>http://www.nowvideo.sx/video/8uqowgafjc9dt</link>
<thumbnail>http://ia.media-imdb.com/images/M/MV5BMTU1Mzc4MzY0Ml5BMl5BanBnXkFtZTcwMDQwODY5OA%40%40._V1_SX214_.jpg</thumbnail>
</item>



<item>
<title>Google and the World Brain (2013)</title>
<link>http://www.putlocker.com/file/60CA44C7D88E48FD#</link>
<thumbnail>http://ia.media-imdb.com/images/M/MV5BMTY0NTk1NjM4M15BMl5BanBnXkFtZTcwNDc3MDc4OA@@._V1_SX640_SY720_.jpg</thumbnail>
</item>

<item>
<title>The Inevitable Defeat of Mister & Pete (2013)</title>
<link>http://movreel.com/ktn569h2kk04#</link>
<thumbnail>http://ia.media-imdb.com/images/M/MV5BMTUwMjgyNTE2OV5BMl5BanBnXkFtZTgwNzU1MzgwMDE@._V1_SX500_SY999_.jpg</thumbnail>
</item>

<item>
<title>Romeo and Juliet (2013)</title>
<link>http://movreel.com/18plpceaudnc#</link>
<thumbnail>http://ia.media-imdb.com/images/M/MV5BMTA3MjQwOTg4MTheQTJeQWpwZ15BbWU3MDM3NDE0OTk@._V1_SX500_SY999_.jpg</thumbnail>
</item>


<item>
<title>Pride & Prejudice TWITTER REQUEST(2005)</title>
<link>http://www.sockshare.com/file/ABC80BD7702C1742#</link>
<thumbnail>http://ia.media-imdb.com/images/M/MV5BMTA1NDQ3NTcyOTNeQTJeQWpwZ15BbWU3MDA0MzA4MzE@._V1_SX640_SY720_.jpg</thumbnail>
</item>

<item>
<title>Filth (2013)</title>
<link>http://movreel.com/ay4wymhhfwea#</link>
<thumbnail>http://ia.media-imdb.com/images/M/MV5BODc3MjY5NTQxNl5BMl5BanBnXkFtZTcwNTQxMzczOQ@@._V1_SX500_SY999_.jpg</thumbnail>
</item>
 
<item>
<title>Against the Grain (2014)</title>
<link>http://hugefiles.net/rd940b8rkkbo</link>
<thumbnail>http://ia.media-imdb.com/images/M/MV5BMjAxMzY2MTIwM15BMl5BanBnXkFtZTcwMzE4MTE2OA@@._V1_SX500_SY999_.jpg</thumbnail>
</item> 

<item>
<title>The Trials of Muhammad Ali (2013)</title>
<link>http://movreel.com/8qrp5xbqr4zl#</link>
<thumbnail>http://ia.media-imdb.com/images/M/MV5BMjM0NDcxMjU2N15BMl5BanBnXkFtZTgwNDE4ODUwMDE@._V1_SX500_SY999_.jpg</thumbnail>
</item>

<item>
<title>In the Name of the King III (2014)</title>
<link>http://vidto.me/ktt6xca7mk9t.html</link>
<thumbnail>http://img.rlsbb.com/images/2014/01/22/in_the_name_of_the_king3_purcell_poster.jpg</thumbnail>
</item>

<item>
<title>Flowers in the Attic (2014)</title>
<link>http://movreel.com/4zb839w97ji4</link>
<thumbnail>http://ia.media-imdb.com/images/M/MV5BMjA4Nzk4MDk4MV5BMl5BanBnXkFtZTgwNjg5ODY5MDE@._V1_SX500_SY999_.jpg</thumbnail>
</item>

<item>
<title>The Hunger Games: Catching Fire (2013) 720p</title>
<link>http://movreel.com/drk8xugel9p7</link>
<thumbnail>http://ia.media-imdb.com/images/M/MV5BMTAyMjQ3OTAxMzNeQTJeQWpwZ15BbWU4MDU0NzA1MzAx._V1_SX500_SY999_.jpg</thumbnail>
</item>

<item>
<title>After the Dark (2013)</title>
<link>http://www.nowvideo.sx/video/3t8vf9pil8w0f</link>
<thumbnail>http://ia.media-imdb.com/images/M/MV5BMjIyNjY4MjM1OV5BMl5BanBnXkFtZTgwMTQyNzE4MDE@._V1_SX640_SY720_.jpg</thumbnail>
</item>

<item>
<title>August: Osage County (2013)</title>
<link>http://www.nowvideo.sx/video/b9012c3880dee</link>
<thumbnail>http://ia.media-imdb.com/images/M/MV5BNzQ5ODE4NTcxNV5BMl5BanBnXkFtZTgwNjkyNDQ0MDE@._V1_SX214_.jpg</thumbnail>
</item>

<item>
<title>The Ganzfeld Haunting (2014)</title>
<link>http://movreel.com/474ufokl2404</link>
<thumbnail>http://ia.media-imdb.com/images/M/MV5BMTc0NTc2MzkzOV5BMl5BanBnXkFtZTgwODMxMjU5MDE@._V1_SX640_SY720_.jpg</thumbnail>
</item>

<item>
<title>Jimmy P. (2013)</title>
<link>http://movreel.com/5ikspq0m7wli</link>
<thumbnail>http://ia.media-imdb.com/images/M/MV5BMTU3NzY4NTAxM15BMl5BanBnXkFtZTgwNDU4MTE5MDE@._V1_SX500_SY999_.jpg</thumbnail>
</item>

<item>
<title>Baggage Claim (2013)</title>
<link>http://movreel.com/2lmcarnz75jz.html</link>
<thumbnail>http://ia.media-imdb.com/images/M/MV5BMjIyNDU4NTY3M15BMl5BanBnXkFtZTcwOTA3MDA1OQ@@._V1_SX640_SY720_.jpg</thumbnail>
</item>

<item>
<title>Due South (1994) TWITTER REQUEST</title>
<link>http://stagevu.com/video/befzbypsazkq</link>
<thumbnail>http://www.tour-de-france.cz/duesouth/images/foto/dvdbox_season4.jpg</thumbnail>
</item>

<item>
<title>The Time Machine (1960)</title>
<link>http://stagevu.com/video/zvpdwjatkucg</link>
<thumbnail>http://ia.media-imdb.com/images/M/MV5BMTYxNzUwMzQ2NF5BMl5BanBnXkFtZTgwNTAwNjk4MDE@._V1_SX640_SY720_.jpg</thumbnail>
</item>

<item>
<title>First Men in the Moon (1964)</title>
<link>http://stagevu.com/video/hfrzapijgnnu</link>
<thumbnail>http://upload.wikimedia.org/wikipedia/en/7/74/FirstMenontheMoon.jpg</thumbnail>
</item>

<item>
<title>The First Men in the Moon (2010) TWITTER REQUEST</title>
<link>http://stagevu.com/video/eiwfdrzmopuk</link>
<thumbnail>http://ia.media-imdb.com/images/M/MV5BMTU0MzIxMzY4Nl5BMl5BanBnXkFtZTcwNDAxNzYxNA@@._V1_SX640_SY720_.jpg</thumbnail>
</item>

<item>
<title>Life of a King (2013)</title>
<link>http://movreel.com/iy8fwgv4vs62</link>
<thumbnail>http://ia.media-imdb.com/images/M/MV5BMjA2MzgzMDM1OV5BMl5BanBnXkFtZTgwMTM5MDI4MDE@._V1_SX500_SY999_.jpg</thumbnail>
</item>

<item>
<title>Reasonable Doubt (2014)</title>
<link>http://movreel.com/lefdw0ype55t</link>
<thumbnail>http://ia.media-imdb.com/images/M/MV5BMTcwMzg2NzI2NF5BMl5BanBnXkFtZTgwNjUzMzU3MDE@._V1_SX500_SY999_.jpg</thumbnail>
</item>

<item>
<title>Dumbbells (2014)</title>
<link>http://movreel.com/f6wi2bphjed2.html</link>
<thumbnail>http://ia.media-imdb.com/images/M/MV5BMTgwODY1NDU5OF5BMl5BanBnXkFtZTgwNjQ4OTA4MDE@._V1_SX640_SY720_.jpg</thumbnail>
</item>

<item>
<title>Forever Young (1992) TWITTER REQUEST</title>
<link>http://movreel.com/778xs8mrit0u</link>
<thumbnail>http://ia.media-imdb.com/images/M/MV5BMTI5MDk2MTIxNF5BMl5BanBnXkFtZTcwMjMwODAwMQ@@._V1_SX640_SY720_.jpg</thumbnail>
</item>

<item>
<title>The Two Worlds of Jennie Logan (1979)  TWITTER REQUEST</title>
<link>http://stagevu.com/video/dmhjmtwhukoq</link>
<thumbnail>http://ia.media-imdb.com/images/M/MV5BMTI5ODkwNTM0Nl5BMl5BanBnXkFtZTcwNTI3OTQ5Mw@@._V1_SX640_SY720_.jpg</thumbnail>
</item>

<item>
<title>Ender's Game (2013)</title>
<link>http://movreel.com/d7ctbgox212f</link>
<thumbnail>http://ia.media-imdb.com/images/M/MV5BMjAzMzI5OTgzMl5BMl5BanBnXkFtZTgwMTU5MTAwMDE@._V1_SX640_SY720_.jpg</thumbnail>
</item>

<item>
<title>Last Ounce of Courage (2012) 720p</title>
<link>http://movreel.com/8cy0ks0b6e9a</link>
<thumbnail>http://ia.media-imdb.com/images/M/MV5BMTY5NjA1NTgzMl5BMl5BanBnXkFtZTcwNDk5MTQ0OA@@._V1_SX500_SY999_.jpg</thumbnail>
</item>

<item>
<title>Insidious: Chapter 2 (2013)</title>
<link>http://www.nowvideo.sx/video/wxtgg62nh109r</link>
<thumbnail>http://ia.media-imdb.com/images/M/MV5BMTg0OTA5ODIxNF5BMl5BanBnXkFtZTcwNTUzNDg4OQ@@._V1_SX500_SY999_.jpg</thumbnail>
</item>

<item>
<title>The Marine 3: Homefront (2013)</title>
<link>http://www.nowvideo.sx/video/vyo20fynxe1rc</link>
<thumbnail>http://ia.media-imdb.com/images/M/MV5BMTg4MDE1NjQ0NV5BMl5BanBnXkFtZTcwOTg2NDg1OQ@@._V1_SX640_SY720_.jpg</thumbnail>
</item>

<item>
<title>Inside Llewyn Davis (2013)</title>
<link>http://movreel.com/p0suj8r95137</link>
<thumbnail>http://ia.media-imdb.com/images/M/MV5BMjAxNjcyNDQxM15BMl5BanBnXkFtZTgwNzU2NDA0MDE@._V1_SX500_SY999_.jpg</thumbnail>
</item>

<item>
<title>Kelly + Victor (2012) 720p</title>
<link>http://movreel.com/4ylps03p63fi</link>
<thumbnail>http://downloadbox.me/uploads/posts/2014-01/1389792720_88506_front.jpg</thumbnail>
</item>

<item>
<title>Lost in Italy (2014)</title>
<link>http://movreel.com/mlnht3ik3f30</link>
<thumbnail>http://ia.media-imdb.com/images/M/MV5BMTQ3OTgyMTQ4NV5BMl5BanBnXkFtZTcwNjM1MTI2OQ@@._V1_SX500_SY999_.jpg</thumbnail>
</item>

<item>
<title>The Book Thief (2013)</title>
<link>http://www.nowvideo.sx/video/88e590fb30378</link>
<thumbnail>http://ia.media-imdb.com/images/M/MV5BOTE3NzkyMjAyNF5BMl5BanBnXkFtZTgwMDc5MTE0MDE@._V1_SX640_SY720_.jpg</thumbnail>
</item>

<item>
<title>Harrigan (2013)</title>
<link>http://movreel.com/kihs236yx9oi</link>
<thumbnail>http://ia.media-imdb.com/images/M/MV5BMTg4MzIzNDkzOV5BMl5BanBnXkFtZTgwMDkwNTQyMDE@._V1_SX500_SY999_.jpg</thumbnail>
</item>

<item>
<title>Once Upon a Time in the West (1968) 720p TWITTER REQUEST</title>
<link>http://movreel.com/cb6ls64hok6z</link>
<thumbnail>http://1.bp.blogspot.com/-ujjUrQPqGeQ/Tew0B_SbqTI/AAAAAAAAJXM/CMCixQnY1bc/s1600/ONCE%252BUPON%252BA%252BTIME%252BIN%252BTHE%252BWEST%252B-%252Bbluray.jpg</thumbnail>
</item>

<item>
<title>The Occupants (2014)</title>
<link>http://www.divxstage.eu/video/d1be12ebb70fb</link>
<thumbnail>http://img.crazyhdsource.com/wp-content/cover/files/The.Occupants.2014.1080p.WEB-DL.DD5.1.H.264.HKD.jpg</thumbnail>
</item>

<item>
<title>$50K and a Call Girl: A Love Story (2014)</title>
<link>http://movreel.com/8fkilllo0k6r</link>
<thumbnail>http://ia.media-imdb.com/images/M/MV5BMTY3OTI0NjY0Ml5BMl5BanBnXkFtZTgwMjUzNjQ2MDE@._V1_SX500_SY999_.jpg</thumbnail>
</item>

<item>
<title>National Lampoon Presents: Surf Party (2013)</title>
<link>http://movreel.com/jl9pybvkebp7</link>
<thumbnail>http://ia.media-imdb.com/images/M/MV5BMTU4MTIzODM5NF5BMl5BanBnXkFtZTcwMzQwMzYwOQ@@._V1_SX500_SY999_.jpg</thumbnail>
</item>

<item>
<title>Instructions Not Included (2013) 720P (Spanish Audio)</title>
<link>http://movreel.com/lo8p4yhboo11</link>
<thumbnail>http://ia.media-imdb.com/images/M/MV5BMTUyNjI3ODI0N15BMl5BanBnXkFtZTcwMTQ1NTY5OQ@@._V1_SX500_SY999_.jpg</thumbnail>
</item>

<item>
<title>In a World... (2013) 720P</title>
<link>http://movreel.com/nhccgogta4ov</link>
<thumbnail>http://ia.media-imdb.com/images/M/MV5BMTU0NzE0Mzg3M15BMl5BanBnXkFtZTcwNzY2MDY3OQ@@._V1_SX500_SY999_.jpg</thumbnail>
</item>

<item>
<title>Supervention (2013) 720P</title>
<link>http://movreel.com/z73rta2p7gbs</link>
<thumbnail>http://ia.media-imdb.com/images/M/MV5BMjE3OTQxMTEyNF5BMl5BanBnXkFtZTgwODMxMzY2MDE@._V1_SX500_SY999_.jpg</thumbnail>
</item>

<item>
<title>Back in the Day (2014)</title>
<link>http://movreel.com/svqa4irz71kx</link>
<thumbnail>http://ia.media-imdb.com/images/M/MV5BMjI4MjA4Mzg2MV5BMl5BanBnXkFtZTgwMTgxMzM3MDE@._V1_SX500_SY999_.jpg</thumbnail>
</item>

<item>
<title>Diana (2013)</title>
<link>http://stagevu.com/video/psykaesbcpep</link>
<thumbnail>http://ia.media-imdb.com/images/M/MV5BMjA0NDg0Njg3N15BMl5BanBnXkFtZTgwMTMxMzMzMDE@._V1_SX640_SY720_.jpg</thumbnail>
</item>

<item>
<title>Once in a Lifetime: The Extraordinary Story of the New York Cosmos (2006)  TWITTER REQUEST</title>
<link>http://www.youtube.com/watch?v=fBR8jN_SyE0</link>
<thumbnail>http://upload.wikimedia.org/wikipedia/en/6/6e/New_York_Cosmos_originalcrest.png</thumbnail>
</item>

<item>
<title>Cold Comes the Night (2013)</title>
<link>http://movreel.com/j9oywkf99wrc</link>
<thumbnail>http://a2.mzstatic.com/us/r30/Video5/v4/8f/6a/45/8f6a459b-c4e0-0cc5-17e7-247af16162f8/COLD_COMES_THE_NIGHT_2013_TH_MLF-WW-artwork.jpg</thumbnail>
</item>

<item>
<title>The Fifth Estate (2013)</title>
<link>http://www.nowvideo.sx/video/0bb71521f20c6</link>
<thumbnail>http://ia.media-imdb.com/images/M/MV5BMjY1MTY5NTg3M15BMl5BanBnXkFtZTgwMDQyMjgwMDE@._V1_SX640_SY720_.jpg</thumbnail>
</item>

<item>
<title>Last Vegas (2013) 720p</title>
<link>http://movreel.com/ccrzhre3c47q</link>
<thumbnail>http://ia.media-imdb.com/images/M/MV5BMTQ2ODg2MTIyNF5BMl5BanBnXkFtZTgwMzU2NjgwMDE@._V1_SX640_SY720_.jpg</thumbnail>
</item>

<item>
<title>Free Ride (2013) 720p</title>
<link>http://movreel.com/6wdiusmle6iq</link>
<thumbnail>http://ia.media-imdb.com/images/M/MV5BOTI1NjExMjEzNl5BMl5BanBnXkFtZTgwNTUzNTM3MDE@._V1_SX640_SY720_.jpg</thumbnail>
</item>

<item>
<title>Grudge Match (2013)</title>
<link>http://www.nowvideo.sx/video/5439b67c7f176</link>
<thumbnail>http://ia.media-imdb.com/images/M/MV5BMTY3NTkxMTgzNV5BMl5BanBnXkFtZTgwNjg0MzE2MDE@._V1_SX640_SY720_.jpg</thumbnail>
</item>

<item>
<title>The Secret Life of Walter Mitty (2013)</title>
<link>http://movreel.com/0hh8mbunv0d8</link>
<thumbnail>http://ia.media-imdb.com/images/M/MV5BODYwNDYxNDk1Nl5BMl5BanBnXkFtZTgwOTAwMTk2MDE@._V1_SX640_SY720_.jpg</thumbnail>
</item>

<item>
<title>9 Songs (2004) TWITTER REQUEST</title>
<link>http://movreel.com/1rznmw2h8rt0</link>
<thumbnail>http://ia.media-imdb.com/images/M/MV5BMTM3ODc4MTI2OV5BMl5BanBnXkFtZTcwMTA4NjUzMQ@@._V1_SX640_SY720_.jpg</thumbnail>
</item>

<item>
<title>Gone with the Wind (1939)  TWITTER REQUEST</title>
<link>http://www.nowvideo.sx/video/5103ee1ae9b9f</link>
<thumbnail>http://ia.media-imdb.com/images/M/MV5BNDUwMjAxNTU1MF5BMl5BanBnXkFtZTgwMzg4NzMxMDE@._V1_SX640_SY720_.jpg</thumbnail>
</item>

<item>
<title>Escape Plan (2013) 720p</title>
<link>http://movreel.com/74u3cpndf0lz</link>
<thumbnail>http://ia.media-imdb.com/images/M/MV5BMTk3OTcxMTEyNl5BMl5BanBnXkFtZTcwMDQ4MjQ2OQ@@._V1_SX640_SY720_.jpg</thumbnail>
</item>

<item>
<title>Scorned (2013)</title>
<link>http://www.nowvideo.sx/video/19debdcd40cc6</link>
<thumbnail>http://ia.media-imdb.com/images/M/MV5BNjUzMTUzMDUwMV5BMl5BanBnXkFtZTgwMjEwODQ3MDE@._V1_SX640_SY720_.jpg</thumbnail>
</item>

<item>
<title>Frozen (2013)</title>
<link>http://www.nowvideo.sx/video/8ndevl85hb2b8</link>
<thumbnail>http://ia.media-imdb.com/images/M/MV5BMTQ1MjQwMTE5OF5BMl5BanBnXkFtZTgwNjk3MTcyMDE@._V1_SX640_SY720_.jpg</thumbnail>
</item>

<item>
<title>I Went Down (1997) TWITTER REQUEST</title>
<link>http://stagevu.com/video/bpvcwlaehiuo</link>
<thumbnail>http://ia.media-imdb.com/images/M/MV5BMTk1Nzk5NTE3OF5BMl5BanBnXkFtZTcwMTIzOTEyMQ@@._V1_SX640_SY720_.jpg</thumbnail>
</item>

<item>
<title>The Adventurer: The Curse of the Midas Box (2014)</title>
<link>http://movreel.com/4wrwx403airw</link>
<thumbnail>http://ia.media-imdb.com/images/M/MV5BNTAwODA2NDUxMF5BMl5BanBnXkFtZTgwNTgyNDc1MDE@._V1_SX640_SY720_.jpg</thumbnail>
</item>

<item>
<title>Coyote Ugly (2000) TWITTER REQUEST</title>
<link>http://www.nowvideo.ch/video/vqjkymx88qq63</link>
<thumbnail>http://ia.media-imdb.com/images/M/MV5BMTk1NzM1ODg4OF5BMl5BanBnXkFtZTcwMTQ3OTgyMQ@@._V1_SY317_CR4,0,214,317_.jpg</thumbnail>
</item>

<item>
<title>Downton Abbey Christmas Special (2013)</title>
<link>http://vidto.me/5o458fk1eb9f.html</link>
<thumbnail>http://ia.media-imdb.com/images/M/MV5BMTg1Nzk1OTIzNV5BMl5BanBnXkFtZTgwNzYwMzE2MDE@._V1_SX640_SY720_.jpg</thumbnail>
</item>

<item>
<title>Fight Club (1999)  TWITTER REQUEST</title>
<link>http://www.nowvideo.sx/video/534dabd5d084e</link>
<thumbnail>http://ia.media-imdb.com/images/M/MV5BMjIwNTYzMzE1M15BMl5BanBnXkFtZTcwOTE5Mzg3OA@@._V1_SX640_SY720_.jpg</thumbnail>
</item>

<item>
<title>Blue Jasmine (2013) 720p</title>
<link>http://movreel.com/g9yuwpc6ms8x</link>
<thumbnail>http://ia.media-imdb.com/images/M/MV5BMTc0ODk5MzEyMV5BMl5BanBnXkFtZTcwMzI0MDY1OQ@@._V1_SX640_SY720_.jpg</thumbnail>
</item>

<item>
<title>Jamesy Boy (2014)</title>
<link>http://movreel.com/0gfth6c3qxkl</link>
<thumbnail>http://ia.media-imdb.com/images/M/MV5BMjM2NjA2NDIzMl5BMl5BanBnXkFtZTgwMTMwOTg1MDE@._V1_SX640_SY720_.jpg</thumbnail>
</item>

<item>
<title>The Goonies (1985) TWITTER REQUEST</title>
<link>http://movreel.com/3qy405vwlxm1</link>
<thumbnail>http://www.ahashare.com/imdbimages/0089218_big.jpg</thumbnail>
</item>

<item>
<title>Dallas Buyers Club (2013)</title>
<link>http://movreel.com/i1am1ziqfnhp</link>
<thumbnail>http://ia.media-imdb.com/images/M/MV5BMTYwMTA4MzgyNF5BMl5BanBnXkFtZTgwMjEyMjE0MDE@._V1_SX214_.jpg</thumbnail>
</item>

<item>
<title>Jackass Presents: Bad Grandpa (2013) 720p</title>
<link>http://movreel.com/1irqgmuiwerk</link>
<thumbnail>http://ia.media-imdb.com/images/M/MV5BMTg4NjIwMTI5OV5BMl5BanBnXkFtZTgwNjU1MTMyMDE@._V1_SX500_SY999_.jpg</thumbnail>
</item>

<item>
<title>Carrie (2013)</title>
<link>http://movreel.com/rbpe1on1y4vr</link>
<thumbnail>http://ia.media-imdb.com/images/M/MV5BMTc1MDIyOTkxN15BMl5BanBnXkFtZTgwMTU1NzEzMDE@._V1_SX500_SY999_.jpg</thumbnail>
</item>

<item>
<title>12 Years a Slave (2013) 720p</title>
<link>http://movreel.com/5esjg65ysldn</link>
<thumbnail>http://ia.media-imdb.com/images/M/MV5BMjExMTEzODkyN15BMl5BanBnXkFtZTcwNTU4NTc4OQ@@._V1_SX640_SY720_.jpg</thumbnail>
</item>

<item>
<title>Bikini Spring Break (2012)</title>
<link>http://movreel.com/t807b0csywg9</link>
<thumbnail>http://ia.media-imdb.com/images/M/MV5BMTg0NjYwNjYyNl5BMl5BanBnXkFtZTcwNjc5NzA2Nw@@._V1_SX500_SY999_.jpg</thumbnail>
</item>

<item>
<title>About Time (2013)</title>
<link>http://movreel.com/98c7cizhfp62</link>
<thumbnail>http://ia.media-imdb.com/images/M/MV5BMTA1ODUzMDA3NzFeQTJeQWpwZ15BbWU3MDgxMTYxNTk@._V1_SX500_SY999_.jpg</thumbnail>
</item>

<item>
<title>The Thirteenth Tale (2013)</title>
<link>http://movreel.com/r04h5k3e9wke</link>
<thumbnail>http://www.eurocrime.co.uk/reviews/T13Tale.jpg</thumbnail>
</item>

<item>
<title>Enough Said (2013)</title>
<link>http://movreel.com/x6lq1etbctu3</link>
<thumbnail>http://ia.media-imdb.com/images/M/MV5BMjI2MjIwMDk2Ml5BMl5BanBnXkFtZTcwNTQ1MzQ5OQ@@._V1_SX500_SY999_.jpg</thumbnail>
</item>

<item>
<title>Freezer (2013)</title>
<link>http://movreel.com/aidpl7g34xqh</link>
<thumbnail>http://ia.media-imdb.com/images/M/MV5BMTgxMzY4MDA4M15BMl5BanBnXkFtZTgwNzE4MzU2MDE@._V1_SX500_SY999_.jpg</thumbnail>
</item>

<item>
<title>Lone Survivor (2013)</title>
<link>http://www.nowvideo.sx/video/7503afd291bd6</link>
<thumbnail>http://ia.media-imdb.com/images/M/MV5BMjA0NTgwOTk5Ml5BMl5BanBnXkFtZTcwMjE3NDc5OQ@@._V1_SX500_SY999_.jpg</thumbnail>
</item>

<item>
<title>American Hustle (2013)</title>
<link>http://movreel.com/wdn5ei4capsd</link>
<thumbnail>http://ia.media-imdb.com/images/M/MV5BNjkxMTc0MDc4N15BMl5BanBnXkFtZTgwODUyNTI1MDE@._V1_SX500_SY999_.jpg</thumbnail>
</item>

<item>
<title>Monster Pies (2013)</title>
<link>http://movreel.com/4vriv6dwg10h</link>
<thumbnail>http://ia.media-imdb.com/images/M/MV5BMTM4NzI3Njk0M15BMl5BanBnXkFtZTcwNzkxNjU0OA@@._V1_SX500_SY999_.jpg</thumbnail>
</item>

<item>
<title>The Selfish Giant (2013)</title>
<link>http://www.nowvideo.sx/video/ef38804c55cf5</link>
<thumbnail>http://ia.media-imdb.com/images/M/MV5BODQyMzUxODEwMF5BMl5BanBnXkFtZTgwOTc5NzE2MDE@._V1_SY317_CR0,0,214,317_.jpg</thumbnail>
</item>

<item>
<title>Vampire Boys 2: The New Brood (2013)</title>
<link>http://www.nowvideo.sx/video/52bf3b0d461ce</link>
<thumbnail>http://ia.media-imdb.com/images/M/MV5BMTQ1OTI3NjQ0M15BMl5BanBnXkFtZTcwOTUyMTI4OA@@._V1_SY317_CR12,0,214,317_.jpg</thumbnail>
</item>

<item>
<title>All Is Lost (2013)</title>
<link>http://www.divxstage.eu/video/62e8b1d2ad1a9</link>
<thumbnail>http://www.impawards.com/2013/posters/all_is_lost_ver3_xlg.jpg</thumbnail>
</item>

<item>
<title>The Hobbit: The Desolation of Smaug (2013) Screener</title>
<link>http://movreel.com/n7yg523sx6u1</link>
<thumbnail>http://ia.media-imdb.com/images/M/MV5BMzU0NDY0NDEzNV5BMl5BanBnXkFtZTgwOTIxNDU1MDE@._V1_SY317_CR0,0,214,317_.jpg</thumbnail>
</item>

<item>
<title>The Last Letter (2013)</title>
<link>http://movreel.com/zzw06a042oei</link>
<thumbnail>http://ia.media-imdb.com/images/M/MV5BMTYyMjQ3MDA0N15BMl5BanBnXkFtZTgwNjQ5MjY2MDE@._V1_SY317_CR1,0,214,317_.jpg</thumbnail>
</item>

<item>
<title>Who Needs Enemies (2013)</title>
<link>http://www.nowvideo.sx/video/xk4unqhnt0fd9</link>
<thumbnail>http://ia.media-imdb.com/images/M/MV5BMTg1NDYxOTA4OV5BMl5BanBnXkFtZTgwODQ0OTU2MDE@._V1_SY317_CR3,0,214,317_.jpg</thumbnail>
</item>

<item>
<title>Christmas Song (2012)</title>
<link>http://www.nowvideo.sx/video/dvn10cp5c5fmn</link>
<thumbnail>http://imgon.net/di-OEN6.jpg</thumbnail>
</item>

<item>
<title>Saving Mr. Banks (2013) Screener</title>
<link>http://movreel.com/6bpd4k5ozbjl</link>
<thumbnail>http://ia.media-imdb.com/images/M/MV5BMTc0MTQ3NzE4Nl5BMl5BanBnXkFtZTcwMzA4NDM5OQ@@._V1_SX214_.jpg</thumbnail>
</item>

<item>
<title>The Butler (2013) HD</title>
<link>http://movreel.com/xr0hcwyavv2a</link>
<thumbnail>http://ia.media-imdb.com/images/M/MV5BMjM2NDY3MjkyMF5BMl5BanBnXkFtZTcwMDM5Nzg5OQ@@._V1_SX214_.jpg</thumbnail>
</item>

<item>
<title>Italian Content Only</title>
<link>http://www.navixtreme.com/playlist/81397/italian_content_only.plx</link>
<thumbnail>http://www.veryicon.com/icon/png/Flag/Not%20a%20Patriot/Italy%20Flag.png</thumbnail>
</item>

<item>
<title>IMDb Top 300  Highest Rated Movies (NEW)</title>
<link>http://www.navixtreme.com/playlist/117480/imdb_top_300_highest_rated_movies_(new).plx</link>
<thumbnail>http://www.orgsc.com/uploads/allimg/c130107/135K25B060-15315.png</thumbnail>
</item>

<item>
<title>Thanks for Sharing (2012) HD</title>
<link>http://movreel.com/h9w6thtiv7h2</link>
<thumbnail>http://ia.media-imdb.com/images/M/MV5BMjA5MzI3ODcxMF5BMl5BanBnXkFtZTcwODY5MTc4OQ@@._V1_SX214_.jpg</thumbnail>
</item>

<item>
<title>The Spectacular Now (2013)</title>
<link>http://movreel.com/1pztodhezpc9</link>
<thumbnail>http://ia.media-imdb.com/images/M/MV5BMjA5MTc0NTkzM15BMl5BanBnXkFtZTcwODEwNjE3OQ@@._V1_SY317_CR0,0,214,317_.jpg</thumbnail>
</item>

<item>
<title>Don Jon (2013)</title>
<link>http://movreel.com/d5an8sb96d1a</link>
<thumbnail>http://ia.media-imdb.com/images/M/MV5BMTQxNTc3NDM2MF5BMl5BanBnXkFtZTcwNzQ5NTQ3OQ@@._V1._CR28,28.649993896484375,1271,1991.0000305175781_SX214_.jpg%20</thumbnail>
</item>

<item>
<title>Mandela: Long Walk to Freedom (2013)</title>
<link>http://movreel.com/0fcy4u7xbi20</link>
<thumbnail>http://ia.media-imdb.com/images/M/MV5BMTg1NTQ1NDczNV5BMl5BanBnXkFtZTcwNDQyMDU1OQ@@._V1_SX214_.jpg</thumbnail>
</item>

<item>
<title>Newlyweeds (2013)</title>
<link>http://www.divxstage.eu/video/37cd6d9520e08</link>
<thumbnail>http://ia.media-imdb.com/images/M/MV5BNzQzMTQyNjM5MF5BMl5BanBnXkFtZTgwOTkwNTQyMDE@._V1_SY317_CR0,0,214,317_.jpg</thumbnail>
</item>

<item>
<title>Out of the Furnace (2013)</title>
<link>http://movreel.com/ubzdesh1mh50</link>
<thumbnail>http://ia.media-imdb.com/images/M/MV5BMTc2MTQ4MDU4NV5BMl5BanBnXkFtZTgwOTU1ODgzMDE@._V1_SX214_.jpg</thumbnail>
</item>

<item>
<title>Runner Runner (2013)</title>
<link>http://movreel.com/5yt018fgwxrf</link>
<thumbnail>http://ia.media-imdb.com/images/M/MV5BMTU5OTA0MjI4Ml5BMl5BanBnXkFtZTgwMTgxOTQwMDE@._V1_SY317_CR0,0,214,317_.jpg</thumbnail>
</item>

<item>
<title>Rush (2013)</title>
<link>http://movreel.com/k0g1z1enuxfz</link>
<thumbnail>http://ia.media-imdb.com/images/M/MV5BMTQyMDE0MTY0OV5BMl5BanBnXkFtZTcwMjI2OTI0OQ@@._V1_SX214_.jpg</thumbnail>
</item>

<item>
<title>Why We Ride (2013)</title>
<link>http://www.divxstage.eu/video/5e24ee61086c5</link>
<thumbnail>http://ia.media-imdb.com/images/M/MV5BMTQzNTEwMDQ5MV5BMl5BanBnXkFtZTgwMzU2NjM2MDE@._V1_SY317_CR0,0,214,317_.jpg</thumbnail>
</item>

<item>
<title>Gravity (2013) 720p</title>
<link>http://movreel.com/hk7n14p7q61c</link>
<thumbnail>http://ia.media-imdb.com/images/M/MV5BNjE5MzYwMzYxMF5BMl5BanBnXkFtZTcwOTk4MTk0OQ@@._V1_SY317_CR0,0,214,317_.jpg</thumbnail>
</item>

<item>
<title>Captain Phillips (2013) 720p</title>
<link>http://movreel.com/ykkjjv4fojis</link>
<thumbnail>http://ia.media-imdb.com/images/M/MV5BMTQzNzExMDg3Ml5BMl5BanBnXkFtZTgwODU1NzEzMDE@._V1_SX214_.jpg</thumbnail>
</item>

<item>
<title>Angel of the Skies (2013)</title>
<link>http://www.divxstage.eu/video/9ea18676f6a60</link>
<thumbnail>http://ia.media-imdb.com/images/M/MV5BMTU2NDY5NjU1M15BMl5BanBnXkFtZTgwOTcxNDE3MDE@._V1_SY317_CR8,0,214,317_.jpg</thumbnail>
</item>

<item>
<title>IMAX-Legends of Flight (2010) HD</title>
<link>http://movreel.com/dd2omhl3447d</link>
<thumbnail>http://ia.media-imdb.com/images/M/MV5BMTk1MzgyMDgwNV5BMl5BanBnXkFtZTcwNTc3MjY2NA@@._V1_SX500_SY999_.jpg</thumbnail>
</item>

<item>
<title>IMAX-Niagara: Miracles, Myths and Magic (1986)</title>
<link>http://movreel.com/5fu4p9aa9f92</link>
<thumbnail>http://ia.media-imdb.com/images/M/MV5BMTQwNzg3NjUzNV5BMl5BanBnXkFtZTcwMzg2MjczMQ@@._V1_SX500_SY999_.jpg</thumbnail>
</item>

<item>
<title>Mike Tyson: Undisputed Truth (2013)</title>
<link>http://movreel.com/j5xjl1ng13uj</link>
<thumbnail>http://3.bp.blogspot.com/-RkwmPbrLKaY/Un_Sw66p08I/AAAAAAAANMM/lJ6-DR_Dir8/s1600/MikeTyson.jpg</thumbnail>
</item>

<item>
<title>The Day Kennedy Died (2013)</title>
<link>http://www.divxstage.eu/video/528ba3188d730</link>
<thumbnail>http://img2-2.timeinc.net/ew/i/2013/10/29/LIFE-The-Day-Kennedy-Died.jpg</thumbnail>
</item>

<item>
<title>Killing Them Softly (2012) TWITTER REQUEST</title>
<link>http://www.videoweed.es/file/0dc17d444248e</link>
<thumbnail>http://ia.media-imdb.com/images/M/MV5BODk3MDg2NDk5M15BMl5BanBnXkFtZTcwMjcxMjMzOA@@._V1_SY317_CR1,0,214,317_.jpg</thumbnail>
</item>

<item>
<title>Nightscape (2012)</title>
<link>http://www.divxstage.eu/video/526a2e7e6914e</link>
<thumbnail>http://ia.media-imdb.com/images/M/MV5BMTU1MTUxOTUzOV5BMl5BanBnXkFtZTcwNjExMzY2Ng@@._V1_SX214_.jpg</thumbnail>
</item>

<item>
<title>Machete Kills (2013)</title>
<link>http://movreel.com/rkwr8li78nq1</link>
<thumbnail>http://ia.media-imdb.com/images/M/MV5BMjA2MzUxMTM3M15BMl5BanBnXkFtZTgwMzA2NzkxMDE@._V1_SX214_.jpg</thumbnail>
</item>

<item>
<title>Getaway (2013)</title>
<link>http://movreel.com/5mac2kgs4x5b</link>
<thumbnail>http://ia.media-imdb.com/images/M/MV5BMTM5NTkzNzk0NF5BMl5BanBnXkFtZTcwMTQwNjE5OQ@@._V1_SY317_CR0,0,214,317_.jpg</thumbnail>
</item>

<item>
<title>The Family (2013) R5</title>
<link>http://www.videoweed.es/file/b7b8877f5a52c</link>
<thumbnail>http://ia.media-imdb.com/images/M/MV5BMjE2MzI0MzkyNV5BMl5BanBnXkFtZTcwMjQ2MDM2OQ@@._V1_SX214_.jpg</thumbnail>
</item>

<item>
<title>Percy Jackson: Sea of Monsters (2013)</title>
<link>http://movreel.com/9l6z8895i3k6</link>
<thumbnail>http://ia.media-imdb.com/images/M/MV5BMTUwODUyODI0Nl5BMl5BanBnXkFtZTcwNzAxODY2OQ@@._V1_SX214_.jpg</thumbnail>
</item>

<item>
<title>STAND-UP COMEDY</title>
<link>http://www.navixtreme.com/playlist/117930/stand-up_comedy.plx</link>
<thumbnail>http://kkcdn-static.kaskus.co.id/images/2013/04/30/5419742_20130430122129.jpg</thumbnail>
</item>

<item>
<title>THE SUPERHERO'S</title>
<link>http://www.navixtreme.com/playlist/125931/the_superheros.plx</link>
<thumbnail>http://www.geeksofdoom.com/GoD/img/2012/12/2012-12-27-marvel_superheroes.jpg</thumbnail>
</item>

<item>
<title>Ultimate Western Collection</title>
<link>http://www.navixtreme.com/playlist/81845/ultimate_western_collection.plx</link>
<thumbnail>http://i1289.photobucket.com/albums/b516/acyyz1958/gunslinger_colored_by_leinilyu_zps7f4fee60.jpg</thumbnail>
</item>

<item>
<title>LIVE in CONCERT</title>
<link>http://www.navixtreme.com/playlist/124402/live_in_concert.plx</link>
<thumbnail>http://i1289.photobucket.com/albums/b516/acyyz1958/LIVEINCONCERT_zps23f60c8b.jpg</thumbnail>
</item>

<item>
<title>FOREIGN CINEMA</title>
<link>http://www.navixtreme.com/playlist/118218/foreign_cinema.plx</link>
<thumbnail>http://i1289.photobucket.com/albums/b516/acyyz1958/FOREIGNCINEMA_zpsd0d0d5ca.png</thumbnail>
</item>

<item>
<title>THE STEPHEN KING COLLECTION</title>
<link>http://www.navixtreme.com/playlist/123147/the_stephen_king_collection.plx</link>
<thumbnail>http://fearlessmen.com/wp-content/uploads/2013/04/Stephen-King-cartoon.png</thumbnail>
</item>

<item>
<title>THE CLINT EASTWOOD COLLECTION</title>
<link>http://www.navixtreme.com/playlist/125827/the_clint_eastwood_collection.plx</link>
<thumbnail>http://images5.fanpop.com/image/photos/25200000/Outlaw-Josey-Wales-clint-eastwood-25240628-1920-1080.jpg</thumbnail>
</item>

<item>
<title>THE BEST OF LIFETIMEURL=http://www.navixtreme.com/playlist/122248/the_best_of_lifetime.plx# 2011848type=playlistname=AMERICAN HORROR STORY (2011 - )</title>
<link>http://www.navixtreme.com/playlist/126269/american_horror_story_(2011_-_).plx</link>
<thumbnail>http://tvafterdarkonline.com/wp-content/uploads/2013/08/American-Horror-Story-Generic-Title-Card.jpg</thumbnail>
</item>

<item>
<title>The Last Days on Mars (2013)</title>
<link>http://www.divxstage.eu/video/feed8bd50e39b</link>
<thumbnail>http://ia.media-imdb.com/images/M/MV5BMTk4ODgxMDU0M15BMl5BanBnXkFtZTgwOTg0NzcyMDE@._V1_SY317_CR0,0,214,317_.jpg</thumbnail>
</item>

<item>
<title>Pacific Rim (2013) 720p</title>
<link>http://movreel.com/8vledh3qvlp3</link>
<thumbnail>http://ia.media-imdb.com/images/M/MV5BMTY3MTI5NjQ4Nl5BMl5BanBnXkFtZTcwOTU1OTU0OQ@@._V1._SX640_SY946_.jpg</thumbnail>
</item>

<item>
<title>9.79* TWITTER REQUEST</title>
<link>http://www.youtube.com/watch?v=jbeb6qB6KPo</link>
<thumbnail>http://themovierat.files.wordpress.com/2012/10/hi-johnson-cp-03398620.jpg</thumbnail>
</item>

<item>
<title>Honor Thy Father (1973) VIEWERS REQUEST</title>
<link>http://stagevu.com/video/debitkfmjrsh</link>
<thumbnail>http://ia.media-imdb.com/images/M/MV5BMTYwMjgwNDA1NV5BMl5BanBnXkFtZTYwOTI5MzE5._V1_SX214_.jpg</thumbnail>
</item>

<item>
<title>The Valachi Papers (1972) VIEWERS REQUEST</title>
<link>http://stagevu.com/video/jxptapqeldeu</link>
<thumbnail>http://ia.media-imdb.com/images/M/MV5BMTI4NDQ5NjIwMV5BMl5BanBnXkFtZTcwMDA2NDYyMQ@@._V1_SX214_.jpg</thumbnail>
</item>

<item>
<title>This Thing of Ours (2003) VIEWERS REQUEST</title>
<link>http://www.youtube.com/watch?v=kTlJqyFSzt4</link>
<thumbnail>http://ia.media-imdb.com/images/M/MV5BMTM5NzE3ODc0N15BMl5BanBnXkFtZTcwMTU3NjQzMQ%40%40._V1_SY317_CR1,0,214,317_.jpg</thumbnail>
</item>

<item>
<title>Family Guy</title>
<link>rtmp://198.27.74.25/app playpath=familyguy01 swfUrl=http://www.tgun.tv/jwplayer/player.swf pageUrl=http://www.tgun.tv/ swfVfy=true live=true</link>
<thumbnail>http://images5.fanpop.com/image/photos/25200000/family-guy-family-guy-25241951-1920-1200.jpg</thumbnail>
</item>
